CHANGELOG.txt
LICENSE.txt
MANIFEST.in
README.txt
setup.py
doc/doc.html
doc/doc.txt
doc/style.css
oejskit/__init__.py
oejskit/browser.py
oejskit/browser_ctl.py
oejskit/htmlrewrite.py
oejskit/modular.py
oejskit/pytest_jstests.py
oejskit/serving.py
oejskit/testing.py
oejskit/unittest_support.py
oejskit/util.py
oejskit/wsgi.py
oejskit.egg-info/PKG-INFO
oejskit.egg-info/SOURCES.txt
oejskit.egg-info/dependency_links.txt
oejskit.egg-info/entry_points.txt
oejskit.egg-info/not-zip-safe
oejskit.egg-info/top_level.txt
oejskit/js/modular_rt.js
oejskit/testing_rt/InBrowserTesting.js
oejskit/testing_rt/abc.txt
oejskit/testing_rt/testing-new.js
oejskit/testing_rt/testing.html
oejskit/testing_rt/utils.js
oejskit/weblib/README
oejskit/weblib/mochikit/LICENSE.txt
oejskit/weblib/mochikit/MochiKit/Async.js
oejskit/weblib/mochikit/MochiKit/Base.js
oejskit/weblib/mochikit/MochiKit/Color.js
oejskit/weblib/mochikit/MochiKit/DOM.js
oejskit/weblib/mochikit/MochiKit/DateTime.js
oejskit/weblib/mochikit/MochiKit/DragAndDrop.js
oejskit/weblib/mochikit/MochiKit/Format.js
oejskit/weblib/mochikit/MochiKit/Iter.js
oejskit/weblib/mochikit/MochiKit/Logging.js
oejskit/weblib/mochikit/MochiKit/LoggingPane.js
oejskit/weblib/mochikit/MochiKit/MochiKit.js
oejskit/weblib/mochikit/MochiKit/MockDOM.js
oejskit/weblib/mochikit/MochiKit/Position.js
oejskit/weblib/mochikit/MochiKit/Selector.js
oejskit/weblib/mochikit/MochiKit/Signal.js
oejskit/weblib/mochikit/MochiKit/Sortable.js
oejskit/weblib/mochikit/MochiKit/Style.js
oejskit/weblib/mochikit/MochiKit/Test.js
oejskit/weblib/mochikit/MochiKit/Visual.js
oejskit/weblib/mochikit/MochiKit/__package__.js
oejskit/weblib/mochikit/doc/html/MochiKit/Async.html
oejskit/weblib/mochikit/doc/html/MochiKit/Base.html
oejskit/weblib/mochikit/doc/html/MochiKit/Color.html
oejskit/weblib/mochikit/doc/html/MochiKit/DOM.html
oejskit/weblib/mochikit/doc/html/MochiKit/DateTime.html
oejskit/weblib/mochikit/doc/html/MochiKit/DragAndDrop.html
oejskit/weblib/mochikit/doc/html/MochiKit/Format.html
oejskit/weblib/mochikit/doc/html/MochiKit/Iter.html
oejskit/weblib/mochikit/doc/html/MochiKit/Logging.html
oejskit/weblib/mochikit/doc/html/MochiKit/LoggingPane.html
