Metadata-Version: 1.0
Name: oejskit
Version: 0.9.0
Summary: Open End JavaScript testing and utility kit
Home-page: http://bitbucket.org/pedronis/js-infrastructure/
Author: Open End AB
Author-email: py-dev@codespeak.net,pedronis@openend.se
License: MIT
Platform: linux
Platform: osx
Platform: win32
Classifier: Development Status :: 4 - Beta
Classifier: Intended Audience :: Developers
Classifier: License :: OSI Approved :: MIT License
Classifier: Operating System :: POSIX
Classifier: Operating System :: Microsoft :: Windows
Classifier: Operating System :: MacOS :: MacOS X
Classifier: Topic :: Software Development :: Testing
Classifier: Topic :: Software Development :: Quality Assurance
Classifier: Topic :: Utilities
Classifier: Programming Language :: Python
Classifier: Programming Language :: JavaScript
